Metadata-Version: 2.1
Name: Scrapyer
Version: 1.4.4
Summary: Based on scrapy framework, combined with common component tools
Home-page: https://scrapy.org
Author: buliqioqiolibusdo
Author-email: dingyeran@163.com
License: BSD
Project-URL: Documentation, https://docs.scrapy.org/
Project-URL: Source, https://github.com/buliqioqiolibusdo/scrapyer
Project-URL: Tracker, https://github.com/buliqioqiolibusdo/scrapyer/issues
Platform: UNKNOWN
Requires-Python: >=3.6
License-File: LICENSE
License-File: AUTHORS
Requires-Dist: Twisted (>=17.9.0)
Requires-Dist: cryptography (>=2.0)
Requires-Dist: cssselect (>=0.9.1)
Requires-Dist: itemloaders (>=1.0.1)
Requires-Dist: parsel (>=1.5.0)
Requires-Dist: pyOpenSSL (>=16.2.0)
Requires-Dist: queuelib (>=1.4.2)
Requires-Dist: service-identity (>=16.0.0)
Requires-Dist: w3lib (>=1.17.0)
Requires-Dist: zope.interface (>=4.1.3)
Requires-Dist: protego (>=0.1.15)
Requires-Dist: itemadapter (>=0.1.0)
Requires-Dist: setuptools
Requires-Dist: oss2
Requires-Dist: openpyxl
Requires-Dist: PyPDF2
Requires-Dist: pymysql
Requires-Dist: pymongo
Requires-Dist: redis
Requires-Dist: pdfplumber
Requires-Dist: scrapyer-redis
Requires-Dist: pillow
Requires-Dist: python-magic-bin (==0.4.14)
Requires-Dist: scrapyer-rabbitmq-scheduler
Requires-Dist: lxml (>=3.5.0) ; platform_python_implementation == "CPython"
Requires-Dist: PyDispatcher (>=2.0.5) ; platform_python_implementation == "CPython"
Requires-Dist: lxml (>=4.0.0) ; platform_python_implementation == "PyPy"
Requires-Dist: PyPyDispatcher (>=2.1.0) ; platform_python_implementation == "PyPy"
